{
    "version": "1.2.0",
    "static_inputs": [
        {
            "key": "PARTICLEPRODUCER_CLASSNAME",
            "value": "BeamParticleProducer"
        },
        {
            "key": "PARTICLES_MASS",
            "value": "1836"
        },
        {
            "key": "PARTICLES_CHARGE",
            "value": "1"
        },
        {
            "key": "PARTICLES_WIDTH",
            "value": "0"
        },
        {
            "key": "PARTICLES_LENGTH",
            "value": "0"
        },
        {
            "key": "REALTIMEREPEATSIMULATION_REMAININGNUMBER",
            "value": "1"
        },
        {
            "key": "PARTICLES_KINETIC_ENERGY",
            "value": "0"
        },
        {
            "key": "PARTICLES_ENERGY_SPREAD",
            "value": "0"
        },
        {
            "key": "PARTICLES_ANGULAR_DIVERGENCE",
            "value": "0"
        },
        {
            "key": "PARTICLES_POLAR_ANGLE",
            "value": "Math.PI/2"
        },
        {
            "key": "PARTICLES_AZIMUTHAL_ANGLE",
            "value": "0"
        },
        {
            "key": "PARTICLES_TRANSLATION_X",
            "value": "0"
        },
        {
            "key": "PARTICLES_TRANSLATION_Y",
            "value": "0"
        },
        {
            "key": "PARTICLES_TRANSLATION_Z",
            "value": "0"
        },
        {
            "key": "FIELD_CLASSNAME",
            "value": "CustomField"
        },
        {
            "key": "CUSTOMFIELD_EX",
            "value": "return x < L/2 && x > -L/2 ? U/L*Math.sin(2*Math.PI*(t+delay)) : 0;"
        },
        {
            "key": "CUSTOMFIELD_EY",
            "value": "return 0;"
        },
        {
            "key": "CUSTOMFIELD_EZ",
            "value": "return 0;"
        },
        {
            "key": "CUSTOMFIELD_BX",
            "value": "return 0;"
        },
        {
            "key": "CUSTOMFIELD_BY",
            "value": "return 0;"
        },
        {
            "key": "CUSTOMFIELD_BZ",
            "value": "return 2*Math.PI*m/q;"
        },
        {
            "key": "LAGUERREGAUSSIANPULSEFIELD_TAU",
            "value": "5 * 2 * Math.PI"
        },
        {
            "key": "LAGUERREGAUSSIANPULSEFIELD_A0",
            "value": "5"
        },
        {
            "key": "LAGUERREGAUSSIANPULSEFIELD_W0",
            "value": "5 * 2 * Math.PI"
        },
        {
            "key": "LAGUERREGAUSSIANPULSEFIELD_EY",
            "value": "0"
        },
        {
            "key": "LAGUERREGAUSSIANPULSEFIELD_DELAY",
            "value": "50 * 2 * Math.PI"
        },
        {
            "key": "LAGUERREGAUSSIANPULSEFIELD_IPHASE",
            "value": "50"
        },
        {
            "key": "LAGUERREGAUSSIANPULSEFIELD_P",
            "value": "0"
        },
        {
            "key": "LAGUERREGAUSSIANPULSEFIELD_L",
            "value": "4"
        },
        {
            "key": "LAGUERREGAUSSIANPULSEFIELD_H",
            "value": "0.1 * 2 * Math.PI"
        },
        {
            "key": "ALGORITHM_CLASSNAME",
            "value": "LeapfrogAlgorithm"
        },
        {
            "key": "REALTIMEREPEATSIMULATION_TIMESTEP",
            "value": "0.0001"
        },
        {
            "key": "REALTIMEREPEATSIMULATION_ENDTIME",
            "value": "20"
        },
        {
            "key": "REALTIMEREPEATSIMULATION_DATASTARTTIME",
            "value": "0"
        },
        {
            "key": "REALTIMEREPEATSIMULATION_DATAINTERVAL",
            "value": "0.01"
        },
        {
            "key": "rateControl_dpf",
            "value": "30"
        },
        {
            "key": "rateControl_fps",
            "value": "25"
        }
    ],
    "customfield_arguments": [
        {
            "key": "q",
            "value": "1"
        },
        {
            "key": "m",
            "value": "1836"
        },
        {
            "key": "U",
            "value": "2000 / 5.11e5"
        },
        {
            "key": "L",
            "value": "0.0005"
        },
        {
            "key": "delay",
            "value": "0.25"
        }
    ],
    "plot_figures": [
        {
            "xAxis": "px",
            "yAxis": "py",
            "figureClass": "Figure2dLine"
        },
        {
            "xAxis": "x",
            "yAxis": "y",
            "figureClass": "Figure2dLine"
        },
        {
            "xAxis": "t",
            "yAxis": "Ek",
            "figureClass": "Figure2dLine"
        }
    ]
}